emoji_getter/__init__.py
emoji_getter-2025.9.1494.dist-info/licenses/LICENSE
emoji_getter-2025.9.1494.dist-info/METADATA
emoji_getter-2025.9.1494.dist-info/WHEEL
emoji_getter-2025.9.1494.dist-info/top_level.txt
emoji_getter-2025.9.1494.dist-info/RECORD
