Metadata-Version: 2.4
Name: emoji_getter
Version: 2025.9.1494
Summary: import re   def emoji_extract(text: str) -> str:     """     Return a string that contains only emoji characters from text.     Heuristic c…
Author-email: Eugene Evstafev <hi@eugene.plus>
License: MIT License
Project-URL: Repository, https://pypi.org/project/emoji_getter/
Requires-Python: >=3.9
License-File: LICENSE
Dynamic: license-file
